powerline_pulseaudio_volume/__init__.py
powerline_pulseaudio_volume/powerline_pulseaudio_volume.py
powerline_pulseaudio_volume_segment-0.1.2.dist-info/LICENSE
powerline_pulseaudio_volume_segment-0.1.2.dist-info/METADATA
powerline_pulseaudio_volume_segment-0.1.2.dist-info/WHEEL
powerline_pulseaudio_volume_segment-0.1.2.dist-info/top_level.txt
powerline_pulseaudio_volume_segment-0.1.2.dist-info/RECORD
