Metadata-Version: 2.1
Name: powerline-pulseaudio-volume-segment
Version: 0.1.2
Summary: Powerline PulseAudio Volume Segment...
Home-page: https://github.com/gmagno/powerline_pulseaudio_volume_segment
Author: Goncalo Magno
Author-email: goncalo.magno@gmail.com
License: MIT license
Keywords: powerline_pulseaudio_volume_segment
Platform: UNKNOWN
Classifier: Development Status :: 2 - Pre-Alpha
Classifier: Intended Audience :: Developers
Classifier: License :: OSI Approved :: MIT License
Classifier: Natural Language :: English
Classifier: Programming Language :: Python :: 3
Classifier: Programming Language :: Python :: 3.6
Classifier: Programming Language :: Python :: 3.7
Classifier: Programming Language :: Python :: 3.8
Requires-Python: >=3.6
Requires-Dist: pulsectl
